README
setup.py
Fujian.egg-info/PKG-INFO
Fujian.egg-info/SOURCES.txt
Fujian.egg-info/dependency_links.txt
Fujian.egg-info/requires.txt
Fujian.egg-info/top_level.txt
fujian/__init__.py
fujian/__main__.py
tests/test_fujian.py