Metadata-Version: 1.1
Name: Fujian
Version: 1.0.0
Summary: An HTTP server that executes Python code.
Home-page: jameson.adjectivenoun.ca/ncoda/fujian
Author: Christopher Antila
Author-email: christopher@antila.ca
License: AGPLv3+
Keywords: tornado,http server,execute python
Platform: UNKNOWN
Classifier: Development Status :: 5 - Production/Stable
Classifier: Programming Language :: Python :: 2.7
Classifier: Programming Language :: Python :: 3.4
Classifier: Programming Language :: Python :: 3.5
Classifier: Programming Language :: Python :: Implementation :: CPython
Classifier: Programming Language :: Python :: Implementation :: PyPy
Classifier: Natural Language :: English
Classifier: Operating System :: OS Independent
Classifier: Topic :: Internet :: WWW/HTTP :: HTTP Servers
Classifier: Topic :: Software Development :: Interpreters
